{"id":"e238b9ae47ff1f90","source_id_to_path":{"0":"E-link contracts/Interfaces/IERC20.sol","1":"E-link contracts/Resolver.sol","2":"E-link contracts/contracts/Escrow.sol","3":"E-link contracts/contracts/EscrowDst.sol","4":"E-link contracts/contracts/EscrowFactory.sol","5":"E-link contracts/contracts/EscrowSrc.sol","6":"lib/forge-std/src/Base.sol","7":"lib/forge-std/src/Script.sol","8":"lib/forge-std/src/StdAssertions.sol","9":"lib/forge-std/src/StdChains.sol","10":"lib/forge-std/src/StdCheats.sol","11":"lib/forge-std/src/StdConstants.sol","12":"lib/forge-std/src/StdError.sol","13":"lib/forge-std/src/StdInvariant.sol","14":"lib/forge-std/src/StdJson.sol","15":"lib/forge-std/src/StdMath.sol","16":"lib/forge-std/src/StdStorage.sol","17":"lib/forge-std/src/StdStyle.sol","18":"lib/forge-std/src/StdToml.sol","19":"lib/forge-std/src/StdUtils.sol","20":"lib/forge-std/src/Test.sol","21":"lib/forge-std/src/Vm.sol","22":"lib/forge-std/src/console.sol","23":"lib/forge-std/src/console2.sol","24":"lib/forge-std/src/interfaces/IMulticall3.sol","25":"lib/forge-std/src/safeconsole.sol","26":"script/Counter.s.sol","27":"src/Resolver.sol","28":"test/Resolver.t.sol"},"language":"Solidity"}